mqtt_chat/__init__.py
mqtt_chat/__main__.py
mqtt_chat/mqtt_chat.py
mqtt_chat-0.1.2.dist-info/LICENSE
mqtt_chat-0.1.2.dist-info/METADATA
mqtt_chat-0.1.2.dist-info/WHEEL
mqtt_chat-0.1.2.dist-info/top_level.txt
mqtt_chat-0.1.2.dist-info/RECORD
