Metadata-Version: 2.1
Name: mqtt-chat
Version: 0.1.2
Summary: light weight mqtt chat client
Home-page: https://github.com/burnish3d/mqtt_chat
Author: Zachary Chandler
Author-email: zachary.c.me@gmail.com
License: MIT
Platform: UNKNOWN
Classifier: Programming Language :: Python :: 3
Classifier: License :: OSI Approved :: MIT License
Requires-Python: >=3.6
License-File: LICENSE
Requires-Dist: paho-mqtt
